Workbook

Sheet Instrucciones
A1: Modelo financiero — Satrack S.A.S. | Fase 4, Reto Linzor
A3: Cómo usar este archivo
A4: 1. Hoja 'Supuestos': todas las celdas amarillas son editables. Cambia cualquiera y el resto del modelo se recalcula solo.
A5: 2. 'Proyección P&L': construye ventas, EBITDA y utilidad neta 2025-2030 a partir de los supuestos de crecimiento y margen.
A6: 3. 'Deuda': calendario simplificado de deuda a 5 años (entrada, intereses, amortización lineal, saldo final).
A7: 4. 'Valuación y Retorno': EV de entrada y salida, ticket de equity de Linzor, MoM/IRR caso base, y tabla de sensibilidad 3x3 (múltiplo entrada x múltiplo salida).
A8: 5. 'Puente de Retorno': descompone la creación de valor en crecimiento de EBITDA, expansión de múltiplo y desapalancamiento.
A10: Convención de colores
A11: Fondo amarillo + texto azul = supuesto editable | Texto negro = fórmula | Texto verde = referencia a otra hoja
A13: Origen de los datos base (2025)
A14: Ventas y EBITDA 2025: SIIS — Superintendencia de Sociedades, corte 2025-12-31, Satrack S.A.S. (NIT 830.059.699).
A15: EBITDA calculado como EBIT + Depreciación y Amortización real (no proxy), según detalle del flujo de efectivo de SIIS.
... A23: confirmados. Declarar esto abiertamente si se pregunta en la defensa oral.

Sheet Supuestos
A1: Supuestos del modelo — Satrack S.A.S.
A3: Datos base (2025)
A4: TRM COP/USD | B4: 3192
A5: Ventas 2025 (COP mm) | B5: 102903 | C5: Fuente: SIIS, Satrack S.A.S., corte 2025-12-31
A6: EBITDA 2025 real (COP mm) | B6: 17856 | C6: EBIT (12,775) + D&A real (5,081), vía flujo de efectivo SIIS
A7: Margen EBITDA 2025 | B7: =B6/B5 -> 0.17352264
A9: Crecimiento
A10: Crecimiento orgánico anual de ventas | B10: 0.13 | C10: Basado en CAGR observado 2024-2025 (~12.8%), ver 03-target-satrack/02-financieros.md
A11: Boost adicional por add-ons (años 2-4, roll-up) | B11: 0.05 | C11: Supuesto — consolidación de competidores más chicos, replicando patrón Numaris
A13: Rentabilidad
A14: Expansión de margen EBITDA anual (pp) | B14: 0.008 | C14: Apalancamiento operativo — ya observado en 2024→2025 (margen subió 8.9pp de EBIT)
A15: D&A (% de ventas, constante) | B15: 0.049 | C15: D&A real 2025 (5,081) dividido entre Ventas 2025 (102,903)
A16: Capex (% de ventas, constante) | B16: 0.045 | C16: ≈ Compras de PP&E 2025 (4,761) / Ventas 2025, vía flujo de inversión SIIS
A18: Estructura de capital
A19: Deuda / EBITDA al cierre (x) | B19: 1 | C19: Conservador, coherente con estilo de underwriting declarado de Linzor
A20: Costo de deuda (tasa anual) | B20: 0.11 | C20: Supuesto — rango típico de crédito corporativo en Colombia
A21: Amortización anual (% saldo inicial, lineal) | B21: 0.2 | C21: Amortización lineal a 5 años (100%/5)
A22: Tasa impositiva corporativa | B22: 0.35 | C22: Tasa de renta corporativa Colombia
A24: Transacción
A25: Múltiplo de entrada — bajo | B25: 6 | C25: Rango razonado, sin comparable de transacción confirmado (ver Instrucciones)
A26: Múltiplo de entrada — base | B26: 7
A27: Múltiplo de entrada — alto | B27: 8
A28: Múltiplo de salida — bajo | B28: 7.5 | C28: Salida a un estratégico regional o fondo más grande, año 5
A29: Múltiplo de salida — base | B29: 8.5
A30: Múltiplo de salida — alto | B30: 9.5
A31: Horizonte de inversión (años) | B31: 5
A32: % Control adquirido por Linzor | B32: 0.8 | C32: Supuesto — posición de control, coherente con la tesis declarada de Linzor

Sheet Proyección P&L
A1: Proyección P&L — Satrack S.A.S. (COP mm salvo indicado)
A3: Rubro | B3: 2025 (base) | C3: 2026 | D3: 2027 | E3: 2028 | F3: 2029 | G3: 2030
A4: Crecimiento total ventas (%) | C4: =Supuestos!$B$10 -> 0.13 | D4: =Supuestos!$B$10+Supuestos!$B$11 -> 0.18 | E4: =Supuestos!$B$10+Supuestos!$B$11 -> 0.18 | F4: =Supuestos!$B$10+Supuestos!$B$11 -> 0.18 | G4: =Supuestos!$B$10 -> 0.13
A5: Ventas (COP mm) | B5: =Supuestos!$B$5 -> 102903 | C5: =B5*(1+C4) -> 116280.39 | D5: =C5*(1+D4) -> 137210.86 | E5: =D5*(1+E4) -> 161908.82 | F5: =E5*(1+F4) -> 191052.4 | G5: =F5*(1+G4) -> 215889.21
A6: Margen EBITDA (%) | B6: =Supuestos!$B$7 -> 0.17352264 | C6: =B6+Supuestos!$B$14 -> 0.18152264 | D6: =C6+Supuestos!$B$14 -> 0.18952264 | E6: =D6+Supuestos!$B$14 -> 0.19752264 | F6: =E6+Supuestos!$B$14 -> 0.20552264 | G6: =F6+Supuestos!$B$14 -> 0.21352264
A7: EBITDA (COP mm) | B7: =B5*B6 -> 17856 | C7: =C5*C6 -> 21107.523 | D7: =D5*D6 -> 26004.564 | E7: =E5*E6 -> 31980.656 | F7: =F5*F6 -> 39265.594 | G7: =G5*G6 -> 46097.234
A8: D&A (COP mm) | B8: =B5*Supuestos!$B$15 -> 5042.247 | C8: =C5*Supuestos!$B$15 -> 5697.7391 | D8: =D5*Supuestos!$B$15 -> 6723.3321 | E8: =E5*Supuestos!$B$15 -> 7933.5319 | F8: =F5*Supuestos!$B$15 -> 9361.5677 | G8: =G5*Supuestos!$B$15 -> 10578.571
A9: EBIT (COP mm) | B9: =B7-B8 -> 12813.753 | C9: =C7-C8 -> 15409.784 | D9: =D7-D8 -> 19281.232 | E9: =E7-E8 -> 24047.124 | F9: =F7-F8 -> 29904.026 | G9: =G7-G8 -> 35518.663
A10: Intereses (COP mm) | C10: =Deuda!C8 -> 1964.16 | D10: =Deuda!D8 -> 1571.328 | E10: =Deuda!E8 -> 1178.496 | F10: =Deuda!F8 -> 785.664 | G10: =Deuda!G8 -> 392.832
A11: EBT (COP mm) | B11: =B9-B10 -> 12813.753 | C11: =C9-C10 -> 13445.624 | D11: =D9-D10 -> 17709.904 | E11: =E9-E10 -> 22868.628 | F11: =F9-F10 -> 29118.362 | G11: =G9-G10 -> 35125.831
A12: Impuestos (COP mm) | B12: =MAX(B11,0)*Supuestos!$B$22 -> 4484.8135 | C12: =MAX(C11,0)*Supuestos!$B$22 -> 4705.9684 | D12: =MAX(D11,0)*Supuestos!$B$22 -> 6198.4664 | E12: =MAX(E11,0)*Supuestos!$B$22 -> 8004.0199 | F12: =MAX(F11,0)*Supuestos!$B$22 -> 10191.427 | G12: =MAX(G11,0)*Supuestos!$B$22 -> 12294.041
A13: Utilidad neta (COP mm) | B13: =B11-B12 -> 8328.9395 | C13: =C11-C12 -> 8739.6556 | D13: =D11-D12 -> 11511.438 | E13: =E11-E12 -> 14864.608 | F13: =F11-F12 -> 18926.935 | G13: =G11-G12 -> 22831.79
A15: Ventas (USD mm) | B15: =B5/Supuestos!$B$4 -> 32.237782 | C15: =C5/Supuestos!$B$4 -> 36.428694 | D15: =D5/Supuestos!$B$4 -> 42.985858 | E15: =E5/Supuestos!$B$4 -> 50.723313 | F15: =F5/Supuestos!$B$4 -> 59.853509 | G15: =G5/Supuestos!$B$4 -> 67.634466
A16: EBITDA (USD mm) | B16: =B7/Supuestos!$B$4 -> 5.593985 | C16: =C7/Supuestos!$B$4 -> 6.6126326 | D16: =D7/Supuestos!$B$4 -> 8.1467933 | E16: =E7/Supuestos!$B$4 -> 10.019003 | F16: =F7/Supuestos!$B$4 -> 12.301251 | G16: =G7/Supuestos!$B$4 -> 14.441489

Sheet Deuda
A1: Calendario de deuda — entrada apalancada, amortización lineal a 5 años
A3: Rubro | B3: 2026 | C3: 2027 | D3: 2028 | E3: 2029 | F3: 2030
A4: Deuda al cierre (entrada, COP mm) | B4: =Supuestos!$B$19*'Proyección P&L'!$B$7 -> 17856
A5: Saldo inicial (COP mm) | C5: =B4 -> 17856 | D5: =C7 -> 14284.8 | E5: =D7 -> 10713.6 | F5: =E7 -> 7142.4 | G5: =F7 -> 3571.2
A6: Amortización (COP mm) | C6: =B4*Supuestos!$B$21 -> 3571.2 | D6: =B4*Supuestos!$B$21 -> 3571.2 | E6: =B4*Supuestos!$B$21 -> 3571.2 | F6: =B4*Supuestos!$B$21 -> 3571.2 | G6: =B4*Supuestos!$B$21 -> 3571.2
A7: Saldo final (COP mm) | C7: =C5-C6 -> 14284.8 | D7: =D5-D6 -> 10713.6 | E7: =E5-E6 -> 7142.4 | F7: =F5-F6 -> 3571.2 | G7: =G5-G6 -> 0
A8: Intereses (COP mm, sobre saldo inicial) | C8: =C5*Supuestos!$B$20 -> 1964.16 | D8: =D5*Supuestos!$B$20 -> 1571.328 | E8: =E5*Supuestos!$B$20 -> 1178.496 | F8: =F5*Supuestos!$B$20 -> 785.664 | G8: =G5*Supuestos!$B$20 -> 392.832

Sheet Valuación y Retorno
A1: Valuación y Retorno — caso base
A3: Entrada (2025 / cierre de la transacción)
A4: EBITDA 2025 (COP mm) | B4: ='Proyección P&L'!B7 -> 17856
A5: EV entrada — bajo (COP mm) | B5: =B4*Supuestos!$B$25 -> 107136
A6: EV entrada — base (COP mm) | B6: =B4*Supuestos!$B$26 -> 124992
A7: EV entrada — alto (COP mm) | B7: =B4*Supuestos!$B$27 -> 142848
A8: Deuda al cierre (COP mm) | B8: =Deuda!B4 -> 17856
A9: Equity value entrada — base (COP mm) | B9: =B6-B8 -> 107136
A10: Ticket equity Linzor — base (COP mm) | B10: =B9*Supuestos!$B$32 -> 85708.8
A11: Ticket equity Linzor — base (USD mm) | B11: =B10/Supuestos!$B$4 -> 26.851128
A13: Salida (año 5 / 2030)
A14: EBITDA salida, año 5 (COP mm) | B14: ='Proyección P&L'!G7 -> 46097.234
A15: EV salida — bajo (COP mm) | B15: =B14*Supuestos!$B$28 -> 345729.26
A16: EV salida — base (COP mm) | B16: =B14*Supuestos!$B$29 -> 391826.49
A17: EV salida — alto (COP mm) | B17: =B14*Supuestos!$B$30 -> 437923.73
A18: Deuda neta salida (COP mm) | B18: =Deuda!G7 -> 0
A19: Equity value salida — base (COP mm) | B19: =B16-B18 -> 391826.49
A20: Proceeds a Linzor — base (COP mm) | B20: =B19*Supuestos!$B$32 -> 313461.19
A21: Proceeds a Linzor — base (USD mm) | B21: =B20/Supuestos!$B$4 -> 98.202129
A23: Retorno — caso base
A24: MoM (Múltiplo sobre el capital) | B24: =B20/B10 -> 3.6572813
A25: IRR | B25: =B24^(1/Supuestos!$B$31)-1 -> 0.2960796
A27: Sensibilidad de MoM — múltiplo entrada (filas) x múltiplo salida (columnas)
A28: Entrada \ Salida | B28: Bajo | C28: Base | D28: Alto
A29: Entrada Bajo | B29: =(B14*Supuestos!$B$28-B18)/(B4*Supuestos!$B$25-B8) -> 3.8724155 | C29: =(B14*Supuestos!$B$29-B18)/(B4*Supuestos!$B$25-B8) -> 4.3887376 | D29: =(B14*Supuestos!$B$30-B18)/(B4*Supuestos!$B$25-B8) -> 4.9050597
A30: Entrada Base | B30: =(B14*Supuestos!$B$28-B18)/(B4*Supuestos!$B$26-B8) -> 3.2270129 | C30: =(B14*Supuestos!$B$29-B18)/(B4*Supuestos!$B$26-B8) -> 3.6572813 | D30: =(B14*Supuestos!$B$30-B18)/(B4*Supuestos!$B$26-B8) -> 4.0875497
A31: Entrada Alto | B31: =(B14*Supuestos!$B$28-B18)/(B4*Supuestos!$B$27-B8) -> 2.7660111 | C31: =(B14*Supuestos!$B$29-B18)/(B4*Supuestos!$B$27-B8) -> 3.1348126 | D31: =(B14*Supuestos!$B$30-B18)/(B4*Supuestos!$B$27-B8) -> 3.503614
A33: Nota: la tabla asume que el % de control y el saldo de deuda no cambian entre escenarios de múltiplo —
A34: solo varía el precio de entrada/salida pagado por el mismo EBITDA. Deuda dimensionada como x EBITDA, no como % del EV.

Sheet Puente de Retorno
A1: Puente de retorno — caso base (descomposición de creación de valor)
A3: Componente | B3: COP mm | C3: % del total
A4: 1. Crecimiento de EBITDA (a múltiplo de entrada constante) | B4: =('Valuación y Retorno'!B14-'Valuación y Retorno'!B4)*Supuestos!$B$26 -> 197688.64 | C4: =B4/B7 -> 0.69439846
A5: 2. Expansión de múltiplo (a EBITDA de salida constante) | B5: ='Valuación y Retorno'!B14*(Supuestos!$B$29-Supuestos!$B$26) -> 69145.852 | C5: =B5/B7 -> 0.24288079
A6: 3. Desapalancamiento (reducción de deuda neta) | B6: ='Valuación y Retorno'!B8-'Valuación y Retorno'!B18 -> 17856 | C6: =B6/B7 -> 0.062720746
A7: Total creación de valor de equity (COP mm) | B7: =B4+B5+B6 -> 284690.49
A9: Verificación: Equity value salida − Equity value entrada (COP mm) | B9: ='Valuación y Retorno'!B19-'Valuación y Retorno'!B9 -> 284690.49
A10: (debe coincidir con el total de arriba)
