Workbook

Sheet Instrucciones
A1: Reto Linzor — Matriz de screening Colombia
A3: Cómo usar este archivo
A4: 1. Hoja 'Ponderaciones': ajusta los pesos de los 5 criterios (deben sumar 100%) y el tipo de cambio COP/USD.
A5: 2. Hoja 'Screening': llena SOLO las celdas amarillas por empresa: NIT, ventas 2023-2025 (COP millones), EBITDA 2025, accionistas, ángulo y los 5 puntajes (1-5).
A6: 3. Las columnas en negro (USD, CAGR, margen, score ponderado, ranking, cumple piso) se calculan solas. No las edites.
A7: 4. Fuente de datos: Portal de Información Empresarial (PIE) de Supersociedades → buscar por NIT o razón social → descargar EEFF. Accionistas: RUES / Cámara de Comercio.
A8: 5. La fila 'EJEMPLO' muestra el formato esperado; bórrala cuando termines.
A10: Convención de colores
A11: Fondo amarillo = celda que tú llenas | Texto azul = supuesto editable | Texto negro = fórmula | Texto verde = referencia a otra hoja
A13: Escala de puntajes (1 = malo, 5 = excelente)
A14: Encaje Linzor: ¿replica un deal previo (Numaris, Sies, Uno Salud, Devlyn)? ¿control posible? ¿historia de impacto ODS 5/8/13?
A15: Tamaño: 5 = ventas US$10-25M y EV estimado US$40-100M; 3 = cerca del piso; 1 = muy por debajo o demasiado grande para LCP IV.
... A20: Confianza en el nombre (columna F): A = sale en ranking sectorial con datos; B = deducido del portafolio de Linzor / conocimiento de mercado, verificar existencia, tamaño y dueño.

Sheet Ponderaciones
A1: Criterio | B1: Peso
A2: Encaje Linzor | B2: 0.3
A3: Tamaño | B3: 0.15
A4: Palanca de valor | B4: 0.2
A5: Ángulo de transacción | B5: 0.2
A6: Disponibilidad de datos | B6: 0.15
A7: Total | B7: =SUM(B2:B6) -> 1 | C7: =IF(ABS(B7-1)<0.0001,"OK","Los pesos deben sumar 100%") -> OK
A9: Tipo de cambio COP por USD (supuesto) | B9: 4000 | C9: Supuesto del usuario; actualizar con TRM vigente (Banco de la República)
A10: Piso de ventas del reto (USD millones) | B10: 10 | C10: Fuente: slide 'Reto Linzor' — ventas anuales sobre ~US$10 millones

Sheet Screening
A1: # | B1: Empresa | C1: Subsector | D1: Ciudad | E1: Qué hace | F1: Confianza nombre | G1: Deal de Linzor que replica | H1: NIT | I1: Ventas 2023 (COP mm) | J1: Ventas 2024 (COP mm) | K1: Ventas 2025 (COP mm) | L1: Ventas 2025 (USD mm) | M1: CAGR 23-25 | N1: EBITDA 2025 (COP mm) | O1: Margen EBITDA | P1: Cumple piso ventas | Q1: Accionistas / dueño | R1: Ángulo de transacción | S1: Encaje Linzor (1-5) | T1: Tamaño (1-5) | U1: Palanca de valor (1-5) | V1: Ángulo transacción (1-5) | W1: Datos (1-5) | X1: Score ponderado | Y1: Ranking | Z1: Notas
A2: ej | B2: EJEMPLO S.A.S. | C2: Software | D2: Bogotá | E2: Fila de ejemplo con formato esperado — borrar | F2: — | G2: Numaris | H2: 900.123.456-7 | I2: 38000 | J2: 44000 | K2: 52000 | L2: =IF(K2="","",K2/Ponderaciones!$B$9) -> 13 | M2: =IF(OR(I2="",K2="",I2<=0),"",(K2/I2)^(1/2)-1) -> 0.1697953 | N2: 9000 | O2: =IF(OR(N2="",K2="",K2=0),"",N2/K2) -> 0.17307692 | P2: =IF(L2="","",IF(L2>=Ponderaciones!$B$10,"SÍ","NO")) -> SÍ | Q2: Fundador 70% / familia 30% | R2: Fundador de 62 años sin sucesor; busca socio para expansión regional | S2: 4 | T2: 4 | U2: 5 | V2: 4 | W2: 5 | X2: =IF(COUNT(S2:W2)<5,"",S2*Ponderaciones!$B$2+T2*Ponderaciones!$B$3+U2*Ponderaciones!$B$4+V2*Ponderaciones!$B$5+W2*Ponderaciones!$B$6) -> 4.35 | Y2: =IF(X2="","",RANK(X2,$X$2:$X$35,0)) -> 1 | Z2: Datos ficticios solo para ilustrar el formato
A3: 1 | B3: Satrack | C3: Software | D3: Medellín | E3: Telemática y gestión de flotas | F3: B | G3: Numaris | H3: 830.059.699 | J3: 91207 | K3: 102903 | L3: =IF(K3="","",K3/Ponderaciones!$B$9) -> 25.72575 | M3: =IF(OR(I3="",K3="",I3<=0),"",(K3/I3)^(1/2)-1) | N3: 12775 | O3: =IF(OR(N3="",K3="",K3=0),"",N3/K3) -> 0.12414604 | P3: =IF(L3="","",IF(L3>=Ponderaciones!$B$10,"SÍ","NO")) -> SÍ | X3: =IF(COUNT(S3:W3)<5,"",S3*Ponderaciones!$B$2+T3*Ponderaciones!$B$3+U3*Ponderaciones!$B$4+V3*Ponderaciones!$B$5+W3*Ponderaciones!$B$6) | Y3: =IF(X3="","",RANK(X3,$X$2:$X$35,0)) | Z3: EBITDA aproximado por EBIT (utilidad operacional); D&A no desagregada en el estado de resultados por función. Fuente: SIIS Supersociedades, corte 2025-12-31.
A4: 2 | B4: Widetech | C4: Software | D4: Bogotá | E4: Telemática, logística, IoT | F4: B | G4: Numaris | L4: =IF(K4="","",K4/Ponderaciones!$B$9) | M4: =IF(OR(I4="",K4="",I4<=0),"",(K4/I4)^(1/2)-1) | O4: =IF(OR(N4="",K4="",K4=0),"",N4/K4) | P4: =IF(L4="","",IF(L4>=Ponderaciones!$B$10,"SÍ","NO")) | Q4: Fundador-operador: Jaime Arbeláez (ingeniero de sistemas, ~55-58 años), fundó la empresa en 2007-2008 tras quedarse sin empleo. Sin fondo visible. | R4: Posible sucesión/liquidez: fundador único, empresa consolidada de ~18 años, presencia en 18+ países. No declara plan de venta pero perfil encaja con institucionalización. | X4: =IF(COUNT(S4:W4)<5,"",S4*Ponderaciones!$B$2+T4*Ponderaciones!$B$3+U4*Ponderaciones!$B$4+V4*Ponderaciones!$B$5+W4*Ponderaciones!$B$6) | Y4: =IF(X4="","",RANK(X4,$X$2:$X$35,0)) | Z4: Fuente: entrevista El Espectador y Rackspace case study. Verificar composición accionaria en Cámara de Comercio.
A5: 3 | B5: Heinsohn Business Technology | C5: Software | D5: Bogotá | E5: Nómina/HR y software para sector público | F5: A | G5: Numaris / inConcert | H5: 800046226 | I5: 130394 | J5: 121137 | K5: 132179 | L5: =IF(K5="","",K5/Ponderaciones!$B$9) -> 33.04475 | M5: =IF(OR(I5="",K5="",I5<=0),"",(K5/I5)^(1/2)-1) -> 0.0068213745 | N5: 27952 | O5: =IF(OR(N5="",K5="",K5=0),"",N5/K5) -> 0.21147081 | P5: =IF(L5="","",IF(L5>=Ponderaciones!$B$10,"SÍ","NO")) -> SÍ | X5: =IF(COUNT(S5:W5)<5,"",S5*Ponderaciones!$B$2+T5*Ponderaciones!$B$3+U5*Ponderaciones!$B$4+V5*Ponderaciones!$B$5+W5*Ponderaciones!$B$6) | Y5: =IF(X5="","",RANK(X5,$X$2:$X$35,0)) | Z5: No se encontró info pública de accionistas/fundador. 40+ años en el mercado, sugiere posible sucesión familiar. Pendiente RUES.
A6: 4 | B6: Digital Ware | C6: Software | D6: Bogotá | E6: ERP (Ophelia) y software hospitalario / HCM | F6: A | G6: Numaris | H6: 830042244 | I6: 82220 | J6: 82029 | K6: 86377 | L6: =IF(K6="","",K6/Ponderaciones!$B$9) -> 21.59425 | M6: =IF(OR(I6="",K6="",I6<=0),"",(K6/I6)^(1/2)-1) -> 0.024968036 | N6: 25597 | O6: =IF(OR(N6="",K6="",K6=0),"",N6/K6) -> 0.29634046 | P6: =IF(L6="","",IF(L6>=Ponderaciones!$B$10,"SÍ","NO")) -> SÍ | Q6: H.I.G. Capital (PE global) — inversión estratégica desde feb-2019, su primera inversión en Colombia. | R6: NO ES TARGET DE ENTRADA: ya tiene sponsor de PE. Obtuvo crédito sindicado COP 38,000mm (Itaú/Davivienda) en abr-2026 para expansión LatAm. Posible salida de H.I.G. en 2-3 años, no ahora. | S6: 1 | X6: =IF(COUNT(S6:W6)<5,"",S6*Ponderaciones!$B$2+T6*Ponderaciones!$B$3+U6*Ponderaciones!$B$4+V6*Ponderaciones!$B$5+W6*Ponderaciones!$B$6) | Y6: =IF(X6="","",RANK(X6,$X$2:$X$35,0)) | Z6: DESCARTAR de la short list activa. Fuente: H.I.G. Capital press release 2019; Cuatrecasas 2026.
A7: 5 | B7: Quipux | C7: Software | D7: Medellín | E7: Software de tránsito y transporte para gobiernos | F7: A | G7: Numaris | H7: 811003486 | I7: 148198 | J7: 184188 | K7: 257372 | L7: =IF(K7="","",K7/Ponderaciones!$B$9) -> 64.343 | M7: =IF(OR(I7="",K7="",I7<=0),"",(K7/I7)^(1/2)-1) -> 0.31783027 | N7: 57588 | O7: =IF(OR(N7="",K7="",K7=0),"",N7/K7) -> 0.22375394 | P7: =IF(L7="","",IF(L7>=Ponderaciones!$B$10,"SÍ","NO")) -> SÍ | X7: =IF(COUNT(S7:W7)<5,"",S7*Ponderaciones!$B$2+T7*Ponderaciones!$B$3+U7*Ponderaciones!$B$4+V7*Ponderaciones!$B$5+W7*Ponderaciones!$B$6) | Y7: =IF(X7="","",RANK(X7,$X$2:$X$35,0)) | Z7: No se encontró info pública de accionistas. Alto riesgo de cliente público (gobiernos). Pendiente RUES.
A8: 6 | B8: Sistemas Expertos | C8: Software | D8: Bogotá | E8: Software hospitalario y facturación en salud | F8: B | G8: Numaris / Sies | L8: =IF(K8="","",K8/Ponderaciones!$B$9) | M8: =IF(OR(I8="",K8="",I8<=0),"",(K8/I8)^(1/2)-1) | O8: =IF(OR(N8="",K8="",K8=0),"",N8/K8) | P8: =IF(L8="","",IF(L8>=Ponderaciones!$B$10,"SÍ","NO")) | X8: =IF(COUNT(S8:W8)<5,"",S8*Ponderaciones!$B$2+T8*Ponderaciones!$B$3+U8*Ponderaciones!$B$4+V8*Ponderaciones!$B$5+W8*Ponderaciones!$B$6) | Y8: =IF(X8="","",RANK(X8,$X$2:$X$35,0))
A9: 7 | B9: Xenco | C9: Software | D9: Bogotá | E9: Software para IPS | F9: B | G9: Numaris / Sies | H9: 811009452 | I9: 12880 | J9: 15954 | K9: 18610 | L9: =IF(K9="","",K9/Ponderaciones!$B$9) -> 4.6525 | M9: =IF(OR(I9="",K9="",I9<=0),"",(K9/I9)^(1/2)-1) -> 0.20202986 | N9: 4208 | O9: =IF(OR(N9="",K9="",K9=0),"",N9/K9) -> 0.22611499 | P9: =IF(L9="","",IF(L9>=Ponderaciones!$B$10,"SÍ","NO")) -> NO | X9: =IF(COUNT(S9:W9)<5,"",S9*Ponderaciones!$B$2+T9*Ponderaciones!$B$3+U9*Ponderaciones!$B$4+V9*Ponderaciones!$B$5+W9*Ponderaciones!$B$6) | Y9: =IF(X9="","",RANK(X9,$X$2:$X$35,0))
A10: 8 | B10: Servinformación Información localizada | C10: Software | D10: Bogotá | E10: Geoanalítica y datos para retail y banca | F10: A | G10: Numaris | H10: 830062674 | I10: 67710 | J10: 106176 | K10: 97421 | L10: =IF(K10="","",K10/Ponderaciones!$B$9) -> 24.35525 | M10: =IF(OR(I10="",K10="",I10<=0),"",(K10/I10)^(1/2)-1) -> 0.19949898 | N10: 6247 | O10: =IF(OR(N10="",K10="",K10=0),"",N10/K10) -> 0.064123752 | P10: =IF(L10="","",IF(L10>=Ponderaciones!$B$10,"SÍ","NO")) -> SÍ | Q10: Propiedad diluida entre profesionales fundadores (empresa 'nace del esfuerzo de un grupo de profesionales'); dirección profesionalizada: CEO Mónica Patiño, luego Manuel Peláez (ejecutivo de carrera, no fundador). | R10: Ángulo fuerte: plan público de expansión a Brasil/México con meta de US$100M en ventas en 5 años. Ya opera en 8 países, vende a 17. Motivo probable: capital para financiar expansión, no sucesión. | X10: =IF(COUNT(S10:W10)<5,"",S10*Ponderaciones!$B$2+T10*Ponderaciones!$B$3+U10*Ponderaciones!$B$4+V10*Ponderaciones!$B$5+W10*Ponderaciones!$B$6) | Y10: =IF(X10="","",RANK(X10,$X$2:$X$35,0)) | Z10: Fuente: entrevista Portafolio 2026 (CEO) y nombramiento Manuel Peláez. Verificar cap table en RUES.
A11: 9 | B11: Siesa | C11: Software | D11: Cali | E11: ERP para empresas medianas | F11: A | G11: Numaris | L11: =IF(K11="","",K11/Ponderaciones!$B$9) | M11: =IF(OR(I11="",K11="",I11<=0),"",(K11/I11)^(1/2)-1) | O11: =IF(OR(N11="",K11="",K11=0),"",N11/K11) | P11: =IF(L11="","",IF(L11>=Ponderaciones!$B$10,"SÍ","NO")) | Q11: Advent International (PE global) adquirió participación mayoritaria en dic-2024, comprándosela a Siesint Holdings (vehículo de Carlos Slim) y exempleados. Cofundador quedó como minoritario. | R11: NO ES TARGET DE ENTRADA: ya es activo de PE global (Advent), comprado hace <2 años. Cualquier entrada sería secundario fondo-a-fondo. | S11: 1 | X11: =IF(COUNT(S11:W11)<5,"",S11*Ponderaciones!$B$2+T11*Ponderaciones!$B$3+U11*Ponderaciones!$B$4+V11*Ponderaciones!$B$5+W11*Ponderaciones!$B$6) | Y11: =IF(X11="","",RANK(X11,$X$2:$X$35,0)) | Z11: DESCARTAR de la short list activa. Fuente: Advent International press release dic-2024, Forbes Colombia.
A12: 10 | B12: Sinco ERP | C12: Software | D12: Bogotá | E12: ERP pyme | F12: B | G12: Numaris | H12: 830021894 | I12: 39854 | J12: 46100 | K12: 57310 | L12: =IF(K12="","",K12/Ponderaciones!$B$9) -> 14.3275 | M12: =IF(OR(I12="",K12="",I12<=0),"",(K12/I12)^(1/2)-1) -> 0.19916583 | N12: 15664 | O12: =IF(OR(N12="",K12="",K12=0),"",N12/K12) -> 0.27332054 | P12: =IF(L12="","",IF(L12>=Ponderaciones!$B$10,"SÍ","NO")) -> SÍ | X12: =IF(COUNT(S12:W12)<5,"",S12*Ponderaciones!$B$2+T12*Ponderaciones!$B$3+U12*Ponderaciones!$B$4+V12*Ponderaciones!$B$5+W12*Ponderaciones!$B$6) | Y12: =IF(X12="","",RANK(X12,$X$2:$X$35,0))
A13: 11 | B13: Novasoft | C13: Software | D13: Bogotá | E13: ERP pyme | F13: B | G13: Numaris | H13: 800028326 | I13: 25939 | J13: 27464 | K13: 30667 | L13: =IF(K13="","",K13/Ponderaciones!$B$9) -> 7.66675 | M13: =IF(OR(I13="",K13="",I13<=0),"",(K13/I13)^(1/2)-1) -> 0.087324145 | N13: 5613 | O13: =IF(OR(N13="",K13="",K13=0),"",N13/K13) -> 0.18303062 | P13: =IF(L13="","",IF(L13>=Ponderaciones!$B$10,"SÍ","NO")) -> NO | X13: =IF(COUNT(S13:W13)<5,"",S13*Ponderaciones!$B$2+T13*Ponderaciones!$B$3+U13*Ponderaciones!$B$4+V13*Ponderaciones!$B$5+W13*Ponderaciones!$B$6) | Y13: =IF(X13="","",RANK(X13,$X$2:$X$35,0))
A14: 12 | B14: Data Tools | C14: Software | D14: Bogotá | E14: Software de facturación y crédito | F14: A | G14: Numaris / Engen | H14: 830031757 | I14: 121745 | J14: 126372 | K14: 175553 | L14: =IF(K14="","",K14/Ponderaciones!$B$9) -> 43.88825 | M14: =IF(OR(I14="",K14="",I14<=0),"",(K14/I14)^(1/2)-1) -> 0.20082179 | N14: 19419 | O14: =IF(OR(N14="",K14="",K14=0),"",N14/K14) -> 0.11061617 | P14: =IF(L14="","",IF(L14>=Ponderaciones!$B$10,"SÍ","NO")) -> SÍ | X14: =IF(COUNT(S14:W14)<5,"",S14*Ponderaciones!$B$2+T14*Ponderaciones!$B$3+U14*Ponderaciones!$B$4+V14*Ponderaciones!$B$5+W14*Ponderaciones!$B$6) | Y14: =IF(X14="","",RANK(X14,$X$2:$X$35,0))
A15: 13 | B15: Ceiba Software House | C15: Software | D15: Medellín | E15: Fábrica de software (servicios) | F15: A | G15: inConcert | H15: 900022972 | I15: 91353 | J15: 95533 | K15: 109218 | L15: =IF(K15="","",K15/Ponderaciones!$B$9) -> 27.3045 | M15: =IF(OR(I15="",K15="",I15<=0),"",(K15/I15)^(1/2)-1) -> 0.0934167 | N15: 11131 | O15: =IF(OR(N15="",K15="",K15=0),"",N15/K15) -> 0.10191544 | P15: =IF(L15="","",IF(L15>=Ponderaciones!$B$10,"SÍ","NO")) -> SÍ | X15: =IF(COUNT(S15:W15)<5,"",S15*Ponderaciones!$B$2+T15*Ponderaciones!$B$3+U15*Ponderaciones!$B$4+V15*Ponderaciones!$B$5+W15*Ponderaciones!$B$6) | Y15: =IF(X15="","",RANK(X15,$X$2:$X$35,0))
A16: 14 | B16: Pragma | C16: Software | D16: Medellín | E16: Fábrica de software (servicios) | F16: A | G16: inConcert | H16: 811004057 | I16: 143990 | J16: 169397 | K16: 197830 | L16: =IF(K16="","",K16/Ponderaciones!$B$9) -> 49.4575 | M16: =IF(OR(I16="",K16="",I16<=0),"",(K16/I16)^(1/2)-1) -> 0.17214114 | N16: 5206 | O16: =IF(OR(N16="",K16="",K16=0),"",N16/K16) -> 0.026315523 | P16: =IF(L16="","",IF(L16>=Ponderaciones!$B$10,"SÍ","NO")) -> SÍ | X16: =IF(COUNT(S16:W16)<5,"",S16*Ponderaciones!$B$2+T16*Ponderaciones!$B$3+U16*Ponderaciones!$B$4+V16*Ponderaciones!$B$5+W16*Ponderaciones!$B$6) | Y16: =IF(X16="","",RANK(X16,$X$2:$X$35,0))
A17: 15 | B17: Sofka Technologies | C17: Software | D17: Medellín | E17: Fábrica de software (servicios) | F17: A | G17: inConcert | H17: 900620832 | I17: 99974 | J17: 109123 | K17: 110734 | L17: =IF(K17="","",K17/Ponderaciones!$B$9) -> 27.6835 | M17: =IF(OR(I17="",K17="",I17<=0),"",(K17/I17)^(1/2)-1) -> 0.052439064 | N17: 2008 | O17: =IF(OR(N17="",K17="",K17=0),"",N17/K17) -> 0.018133545 | P17: =IF(L17="","",IF(L17>=Ponderaciones!$B$10,"SÍ","NO")) -> SÍ | X17: =IF(COUNT(S17:W17)<5,"",S17*Ponderaciones!$B$2+T17*Ponderaciones!$B$3+U17*Ponderaciones!$B$4+V17*Ponderaciones!$B$5+W17*Ponderaciones!$B$6) | Y17: =IF(X17="","",RANK(X17,$X$2:$X$35,0))
A18: 16 | B18: Asesoftware | C18: Software | D18: Bogotá | E18: Fábrica de software (servicios) | F18: A | G18: inConcert | H18: 800135532 | I18: 70033 | J18: 72202 | K18: 39508 | L18: =IF(K18="","",K18/Ponderaciones!$B$9) -> 9.877 | M18: =IF(OR(I18="",K18="",I18<=0),"",(K18/I18)^(1/2)-1) -> -0.24891142 | N18: 5191 | O18: =IF(OR(N18="",K18="",K18=0),"",N18/K18) -> 0.13139111 | P18: =IF(L18="","",IF(L18>=Ponderaciones!$B$10,"SÍ","NO")) -> NO | X18: =IF(COUNT(S18:W18)<5,"",S18*Ponderaciones!$B$2+T18*Ponderaciones!$B$3+U18*Ponderaciones!$B$4+V18*Ponderaciones!$B$5+W18*Ponderaciones!$B$6) | Y18: =IF(X18="","",RANK(X18,$X$2:$X$35,0))
A19: 17 | B19: Alegra | C19: Software | D19: Bogotá | E19: Contabilidad SaaS pymes (VC) | F19: B | G19: — | H19: 900559088 | I19: 38409 | J19: 53710 | K19: 68932945 | L19: =IF(K19="","",K19/Ponderaciones!$B$9) -> 17233.236 | M19: =IF(OR(I19="",K19="",I19<=0),"",(K19/I19)^(1/2)-1) -> 41.363996 | N19: 10186 | O19: =IF(OR(N19="",K19="",K19=0),"",N19/K19) -> 0.00014776679 | P19: =IF(L19="","",IF(L19>=Ponderaciones!$B$10,"SÍ","NO")) -> SÍ | X19: =IF(COUNT(S19:W19)<5,"",S19*Ponderaciones!$B$2+T19*Ponderaciones!$B$3+U19*Ponderaciones!$B$4+V19*Ponderaciones!$B$5+W19*Ponderaciones!$B$6) | Y19: =IF(X19="","",RANK(X19,$X$2:$X$35,0)) | Z19: EBIT negativo el periodo anterior 2024
A20: 18 | B20: Dumian Medical | C20: Salud | D20: Cali | E20: IPS gestión de enfermedades crónicas | F20: A | G20: Sies Salud | L20: =IF(K20="","",K20/Ponderaciones!$B$9) | M20: =IF(OR(I20="",K20="",I20<=0),"",(K20/I20)^(1/2)-1) | O20: =IF(OR(N20="",K20="",K20=0),"",N20/K20) | P20: =IF(L20="","",IF(L20>=Ponderaciones!$B$10,"SÍ","NO")) | X20: =IF(COUNT(S20:W20)<5,"",S20*Ponderaciones!$B$2+T20*Ponderaciones!$B$3+U20*Ponderaciones!$B$4+V20*Ponderaciones!$B$5+W20*Ponderaciones!$B$6) | Y20: =IF(X20="","",RANK(X20,$X$2:$X$35,0))
A21: 19 | B21: Medicarte | C21: Salud | D21: Medellín | E21: Crónicos, VIH, alto costo | F21: B | G21: Sies Salud | L21: =IF(K21="","",K21/Ponderaciones!$B$9) | M21: =IF(OR(I21="",K21="",I21<=0),"",(K21/I21)^(1/2)-1) | O21: =IF(OR(N21="",K21="",K21=0),"",N21/K21) | P21: =IF(L21="","",IF(L21>=Ponderaciones!$B$10,"SÍ","NO")) | X21: =IF(COUNT(S21:W21)<5,"",S21*Ponderaciones!$B$2+T21*Ponderaciones!$B$3+U21*Ponderaciones!$B$4+V21*Ponderaciones!$B$5+W21*Ponderaciones!$B$6) | Y21: =IF(X21="","",RANK(X21,$X$2:$X$35,0))
A22: 20 | B22: IMAT Oncomédica | C22: Salud | D22: Montería | E22: Oncología en el Caribe | F22: A | G22: Sies Salud | L22: =IF(K22="","",K22/Ponderaciones!$B$9) | M22: =IF(OR(I22="",K22="",I22<=0),"",(K22/I22)^(1/2)-1) | O22: =IF(OR(N22="",K22="",K22=0),"",N22/K22) | P22: =IF(L22="","",IF(L22>=Ponderaciones!$B$10,"SÍ","NO")) | Q22: Grupo Auna (inversionista peruano Jesús Zamora, vía holding Enfoca) adquirió 70% de Oncomédica en 2025, tomando control de IMAT y de la Clínica Universitaria Medicina Integral. | R22: NO ES TARGET: ya es parte de un consolidador regional (Auna opera 23 centros en Perú, Colombia y México). Auna es más bien un comprador estratégico potencial para OTRO target de Linzor, no un target en sí. | S22: 1 | X22: =IF(COUNT(S22:W22)<5,"",S22*Ponderaciones!$B$2+T22*Ponderaciones!$B$3+U22*Ponderaciones!$B$4+V22*Ponderaciones!$B$5+W22*Ponderaciones!$B$6) | Y22: =IF(X22="","",RANK(X22,$X$2:$X$35,0)) | Z22: DESCARTAR de la short list activa. Fuente: Las2Orillas. Auna anotar como comprador estratégico potencial para salida.
A23: 21 | B23: Bienestar IPS | C23: Salud | D23: Varias | E23: IPS ambulatoria mediana | F23: A | G23: Sies Salud | L23: =IF(K23="","",K23/Ponderaciones!$B$9) | M23: =IF(OR(I23="",K23="",I23<=0),"",(K23/I23)^(1/2)-1) | O23: =IF(OR(N23="",K23="",K23=0),"",N23/K23) | P23: =IF(L23="","",IF(L23>=Ponderaciones!$B$10,"SÍ","NO")) | X23: =IF(COUNT(S23:W23)<5,"",S23*Ponderaciones!$B$2+T23*Ponderaciones!$B$3+U23*Ponderaciones!$B$4+V23*Ponderaciones!$B$5+W23*Ponderaciones!$B$6) | Y23: =IF(X23="","",RANK(X23,$X$2:$X$35,0))
A24: 22 | B24: Clínica Medical | C24: Salud | D24: Varias | E24: IPS ambulatoria mediana | F24: A | G24: Sies Salud | L24: =IF(K24="","",K24/Ponderaciones!$B$9) | M24: =IF(OR(I24="",K24="",I24<=0),"",(K24/I24)^(1/2)-1) | O24: =IF(OR(N24="",K24="",K24=0),"",N24/K24) | P24: =IF(L24="","",IF(L24>=Ponderaciones!$B$10,"SÍ","NO")) | X24: =IF(COUNT(S24:W24)<5,"",S24*Ponderaciones!$B$2+T24*Ponderaciones!$B$3+U24*Ponderaciones!$B$4+V24*Ponderaciones!$B$5+W24*Ponderaciones!$B$6) | Y24: =IF(X24="","",RANK(X24,$X$2:$X$35,0))
A25: 23 | B25: Sonría | C25: Salud | D25: Bogotá | E25: Cadena de clínicas dentales | F25: B | G25: Uno Salud Dental | L25: =IF(K25="","",K25/Ponderaciones!$B$9) | M25: =IF(OR(I25="",K25="",I25<=0),"",(K25/I25)^(1/2)-1) | O25: =IF(OR(N25="",K25="",K25=0),"",N25/K25) | P25: =IF(L25="","",IF(L25>=Ponderaciones!$B$10,"SÍ","NO")) | Q25: Posible ronda de growth equity ya recibida (Dealroom indica 'Growth Equity VC', monto no revelado). Gerente general Robin Gutiérrez (parece ejecutivo profesional, no necesariamente fundador-dueño). | R25: Verificar con urgencia si el inversor de growth equity tiene control o es minoritario antes de avanzar — cambia todo el ángulo de entrada. 62 clínicas propias + Colordent (laboratorio) + operación en México (11 clínicas) — puede ser demasiado grande para el ticket de LCP IV. | X25: =IF(COUNT(S25:W25)<5,"",S25*Ponderaciones!$B$2+T25*Ponderaciones!$B$3+U25*Ponderaciones!$B$4+V25*Ponderaciones!$B$5+W25*Ponderaciones!$B$6) | Y25: =IF(X25="","",RANK(X25,$X$2:$X$35,0)) | Z25: PRIORIDAD DE VERIFICACIÓN ALTA. Fuente: Dealroom, Portafolio 2025, Crunchbase.
A26: 24 | B26: Dentisalud | C26: Salud | D26: Bogotá | E26: Cadena dental | F26: B | G26: Uno Salud Dental | L26: =IF(K26="","",K26/Ponderaciones!$B$9) | M26: =IF(OR(I26="",K26="",I26<=0),"",(K26/I26)^(1/2)-1) | O26: =IF(OR(N26="",K26="",K26=0),"",N26/K26) | P26: =IF(L26="","",IF(L26>=Ponderaciones!$B$10,"SÍ","NO")) | X26: =IF(COUNT(S26:W26)<5,"",S26*Ponderaciones!$B$2+T26*Ponderaciones!$B$3+U26*Ponderaciones!$B$4+V26*Ponderaciones!$B$5+W26*Ponderaciones!$B$6) | Y26: =IF(X26="","",RANK(X26,$X$2:$X$35,0))
A27: 25 | B27: Dinámica IPS | C27: Salud | D27: Medellín | E27: Diagnóstico por imágenes | F27: B | G27: Sies / Uno Salud | L27: =IF(K27="","",K27/Ponderaciones!$B$9) | M27: =IF(OR(I27="",K27="",I27<=0),"",(K27/I27)^(1/2)-1) | O27: =IF(OR(N27="",K27="",K27=0),"",N27/K27) | P27: =IF(L27="","",IF(L27>=Ponderaciones!$B$10,"SÍ","NO")) | X27: =IF(COUNT(S27:W27)<5,"",S27*Ponderaciones!$B$2+T27*Ponderaciones!$B$3+U27*Ponderaciones!$B$4+V27*Ponderaciones!$B$5+W27*Ponderaciones!$B$6) | Y27: =IF(X27="","",RANK(X27,$X$2:$X$35,0))
A28: 26 | B28: Idime | C28: Salud | D28: Bogotá | E28: Imágenes diagnósticas | F28: B | G28: Sies / Uno Salud | L28: =IF(K28="","",K28/Ponderaciones!$B$9) | M28: =IF(OR(I28="",K28="",I28<=0),"",(K28/I28)^(1/2)-1) | O28: =IF(OR(N28="",K28="",K28=0),"",N28/K28) | P28: =IF(L28="","",IF(L28>=Ponderaciones!$B$10,"SÍ","NO")) | X28: =IF(COUNT(S28:W28)<5,"",S28*Ponderaciones!$B$2+T28*Ponderaciones!$B$3+U28*Ponderaciones!$B$4+V28*Ponderaciones!$B$5+W28*Ponderaciones!$B$6) | Y28: =IF(X28="","",RANK(X28,$X$2:$X$35,0))
A29: 27 | B29: Colcan | C29: Salud | D29: Bogotá | E29: Laboratorio clínico | F29: B | G29: — | L29: =IF(K29="","",K29/Ponderaciones!$B$9) | M29: =IF(OR(I29="",K29="",I29<=0),"",(K29/I29)^(1/2)-1) | O29: =IF(OR(N29="",K29="",K29=0),"",N29/K29) | P29: =IF(L29="","",IF(L29>=Ponderaciones!$B$10,"SÍ","NO")) | X29: =IF(COUNT(S29:W29)<5,"",S29*Ponderaciones!$B$2+T29*Ponderaciones!$B$3+U29*Ponderaciones!$B$4+V29*Ponderaciones!$B$5+W29*Ponderaciones!$B$6) | Y29: =IF(X29="","",RANK(X29,$X$2:$X$35,0))
A30: 28 | B30: Lafam | C30: Salud | D30: Bogotá | E30: Cadena de ópticas | F30: B | G30: Devlyn | H30: 900407148 | I30: 115807 | J30: 118367 | K30: 121892 | L30: =IF(K30="","",K30/Ponderaciones!$B$9) -> 30.473 | M30: =IF(OR(I30="",K30="",I30<=0),"",(K30/I30)^(1/2)-1) -> 0.025935826 | N30: 18824 | O30: =IF(OR(N30="",K30="",K30=0),"",N30/K30) -> 0.15443179 | P30: =IF(L30="","",IF(L30>=Ponderaciones!$B$10,"SÍ","NO")) -> SÍ | X30: =IF(COUNT(S30:W30)<5,"",S30*Ponderaciones!$B$2+T30*Ponderaciones!$B$3+U30*Ponderaciones!$B$4+V30*Ponderaciones!$B$5+W30*Ponderaciones!$B$6) | Y30: =IF(X30="","",RANK(X30,$X$2:$X$35,0))
A31: 29 | B31: Clínica de Oftalmología San Diego | C31: Salud | D31: Medellín | E31: Cirugía oftalmológica | F31: B | G31: Devlyn / Uno Salud | L31: =IF(K31="","",K31/Ponderaciones!$B$9) | M31: =IF(OR(I31="",K31="",I31<=0),"",(K31/I31)^(1/2)-1) | O31: =IF(OR(N31="",K31="",K31=0),"",N31/K31) | P31: =IF(L31="","",IF(L31>=Ponderaciones!$B$10,"SÍ","NO")) | X31: =IF(COUNT(S31:W31)<5,"",S31*Ponderaciones!$B$2+T31*Ponderaciones!$B$3+U31*Ponderaciones!$B$4+V31*Ponderaciones!$B$5+W31*Ponderaciones!$B$6) | Y31: =IF(X31="","",RANK(X31,$X$2:$X$35,0))
A32: 30 | B32: Oftalmos | C32: Salud | D32: Bogotá | E32: Cirugía oftalmológica | F32: B | G32: Devlyn / Uno Salud | L32: =IF(K32="","",K32/Ponderaciones!$B$9) | M32: =IF(OR(I32="",K32="",I32<=0),"",(K32/I32)^(1/2)-1) | O32: =IF(OR(N32="",K32="",K32=0),"",N32/K32) | P32: =IF(L32="","",IF(L32>=Ponderaciones!$B$10,"SÍ","NO")) | X32: =IF(COUNT(S32:W32)<5,"",S32*Ponderaciones!$B$2+T32*Ponderaciones!$B$3+U32*Ponderaciones!$B$4+V32*Ponderaciones!$B$5+W32*Ponderaciones!$B$6) | Y32: =IF(X32="","",RANK(X32,$X$2:$X$35,0))
A33: 31 | B33: Medplus | C33: Salud | D33: Bogotá | E33: Prepagada / plan complementario | F33: B | G33: Cruz Blanca / Banmédica | L33: =IF(K33="","",K33/Ponderaciones!$B$9) | M33: =IF(OR(I33="",K33="",I33<=0),"",(K33/I33)^(1/2)-1) | O33: =IF(OR(N33="",K33="",K33=0),"",N33/K33) | P33: =IF(L33="","",IF(L33>=Ponderaciones!$B$10,"SÍ","NO")) | Q33: Grupo familiar MedPlus Holding (13-14 empresas). Presidente ejecutivo de larga data: J. Hernando Botero (>4 años en el cargo, dirige hace tiempo la expansión del holding). | R33: Probablemente DEMASIADO GRANDE para LCP IV: ha invertido >COP 100,000mm solo en una clínica (Clínica Azul) y otros COP 100,000mm en Clínica Santa Mónica. Sin señal de venta — están invirtiendo capital propio agresivamente, no buscando socio. | T33: 2 | X33: =IF(COUNT(S33:W33)<5,"",S33*Ponderaciones!$B$2+T33*Ponderaciones!$B$3+U33*Ponderaciones!$B$4+V33*Ponderaciones!$B$5+W33*Ponderaciones!$B$6) | Y33: =IF(X33="","",RANK(X33,$X$2:$X$35,0)) | Z33: Bajar prioridad por tamaño y falta de ángulo de transacción. Fuente: La República, Valora Analitik, La Nota Económica.
A34: 32 | B34: Emermédica | C34: Salud | D34: Bogotá | E34: Atención domiciliaria prepagada | F34: B | G34: Cruz Blanca | L34: =IF(K34="","",K34/Ponderaciones!$B$9) | M34: =IF(OR(I34="",K34="",I34<=0),"",(K34/I34)^(1/2)-1) | O34: =IF(OR(N34="",K34="",K34=0),"",N34/K34) | P34: =IF(L34="","",IF(L34>=Ponderaciones!$B$10,"SÍ","NO")) | X34: =IF(COUNT(S34:W34)<5,"",S34*Ponderaciones!$B$2+T34*Ponderaciones!$B$3+U34*Ponderaciones!$B$4+V34*Ponderaciones!$B$5+W34*Ponderaciones!$B$6) | Y34: =IF(X34="","",RANK(X34,$X$2:$X$35,0))
A35: 33 | B35: EMI | C35: Salud | D35: Medellín | E35: Atención domiciliaria prepagada | F35: B | G35: Cruz Blanca | L35: =IF(K35="","",K35/Ponderaciones!$B$9) | M35: =IF(OR(I35="",K35="",I35<=0),"",(K35/I35)^(1/2)-1) | O35: =IF(OR(N35="",K35="",K35=0),"",N35/K35) | P35: =IF(L35="","",IF(L35>=Ponderaciones!$B$10,"SÍ","NO")) | X35: =IF(COUNT(S35:W35)<5,"",S35*Ponderaciones!$B$2+T35*Ponderaciones!$B$3+U35*Ponderaciones!$B$4+V35*Ponderaciones!$B$5+W35*Ponderaciones!$B$6) | Y35: =IF(X35="","",RANK(X35,$X$2:$X$35,0))
B37: Leyenda: amarillo = llenar; verde = referencia a Ponderaciones; negro = fórmula. Ventas y EBITDA en COP millones tal como reporta Supersociedades.
B38: Fuentes de nombres: rankings sectoriales LaNota (TI 2025, IPS 2024) = confianza A; deducidos del portafolio de Linzor = confianza B.

Sheet Shortlist
A1: Top 5 por score ponderado (se actualiza solo cuando llenas los puntajes)
A3: Posición | B3: Empresa | C3: Subsector | D3: Score | E3: Ventas 2025 (USD mm) | F3: Cumple piso
A4: 1 | B4: =IFERROR(INDEX(Screening!$B$2:$B$35,MATCH(1,Screening!$Y$2:$Y$35,0)),"") -> EJEMPLO S.A.S. | C4: =IFERROR(INDEX(Screening!$C$2:$C$35,MATCH(1,Screening!$Y$2:$Y$35,0)),"") -> Software | D4: =IFERROR(INDEX(Screening!$X$2:$X$35,MATCH(1,Screening!$Y$2:$Y$35,0)),"") -> 4.35 | E4: =IFERROR(INDEX(Screening!$L$2:$L$35,MATCH(1,Screening!$Y$2:$Y$35,0)),"") -> 13 | F4: =IFERROR(INDEX(Screening!$P$2:$P$35,MATCH(1,Screening!$Y$2:$Y$35,0)),"") -> SÍ
A5: 2 | B5: =IFERROR(INDEX(Screening!$B$2:$B$35,MATCH(2,Screening!$Y$2:$Y$35,0)),"") | C5: =IFERROR(INDEX(Screening!$C$2:$C$35,MATCH(2,Screening!$Y$2:$Y$35,0)),"") | D5: =IFERROR(INDEX(Screening!$X$2:$X$35,MATCH(2,Screening!$Y$2:$Y$35,0)),"") | E5: =IFERROR(INDEX(Screening!$L$2:$L$35,MATCH(2,Screening!$Y$2:$Y$35,0)),"") | F5: =IFERROR(INDEX(Screening!$P$2:$P$35,MATCH(2,Screening!$Y$2:$Y$35,0)),"")
A6: 3 | B6: =IFERROR(INDEX(Screening!$B$2:$B$35,MATCH(3,Screening!$Y$2:$Y$35,0)),"") | C6: =IFERROR(INDEX(Screening!$C$2:$C$35,MATCH(3,Screening!$Y$2:$Y$35,0)),"") | D6: =IFERROR(INDEX(Screening!$X$2:$X$35,MATCH(3,Screening!$Y$2:$Y$35,0)),"") | E6: =IFERROR(INDEX(Screening!$L$2:$L$35,MATCH(3,Screening!$Y$2:$Y$35,0)),"") | F6: =IFERROR(INDEX(Screening!$P$2:$P$35,MATCH(3,Screening!$Y$2:$Y$35,0)),"")
A7: 4 | B7: =IFERROR(INDEX(Screening!$B$2:$B$35,MATCH(4,Screening!$Y$2:$Y$35,0)),"") | C7: =IFERROR(INDEX(Screening!$C$2:$C$35,MATCH(4,Screening!$Y$2:$Y$35,0)),"") | D7: =IFERROR(INDEX(Screening!$X$2:$X$35,MATCH(4,Screening!$Y$2:$Y$35,0)),"") | E7: =IFERROR(INDEX(Screening!$L$2:$L$35,MATCH(4,Screening!$Y$2:$Y$35,0)),"") | F7: =IFERROR(INDEX(Screening!$P$2:$P$35,MATCH(4,Screening!$Y$2:$Y$35,0)),"")
A8: 5 | B8: =IFERROR(INDEX(Screening!$B$2:$B$35,MATCH(5,Screening!$Y$2:$Y$35,0)),"") | C8: =IFERROR(INDEX(Screening!$C$2:$C$35,MATCH(5,Screening!$Y$2:$Y$35,0)),"") | D8: =IFERROR(INDEX(Screening!$X$2:$X$35,MATCH(5,Screening!$Y$2:$Y$35,0)),"") | E8: =IFERROR(INDEX(Screening!$L$2:$L$35,MATCH(5,Screening!$Y$2:$Y$35,0)),"") | F8: =IFERROR(INDEX(Screening!$P$2:$P$35,MATCH(5,Screening!$Y$2:$Y$35,0)),"")
